ticktick_to_sqlite/__init__.py
ticktick_to_sqlite/__main__.py
ticktick_to_sqlite/cli.py
ticktick_to_sqlite/utils.py
ticktick_to_sqlite-0.1.0.dist-info/LICENSE
ticktick_to_sqlite-0.1.0.dist-info/METADATA
ticktick_to_sqlite-0.1.0.dist-info/WHEEL
ticktick_to_sqlite-0.1.0.dist-info/entry_points.txt
ticktick_to_sqlite-0.1.0.dist-info/top_level.txt
ticktick_to_sqlite-0.1.0.dist-info/RECORD
