Metadata-Version: 2.1
Name: ticktick-to-sqlite
Version: 0.1.0
Summary: Import TickTick data into a SQLite database
Author: Scott Carvalho
License: Apache-2.0
Project-URL: Homepage, https://github.com/Scarvy/ticktick-to-sqlite
Project-URL: Changelog, https://github.com/Scarvy/ticktick-to-sqlite/releases
Project-URL: Issues, https://github.com/Scarvy/ticktick-to-sqlite/issues
Project-URL: CI, https://github.com/Scarvy/ticktick-to-sqlite/actions
Classifier: License :: OSI Approved :: Apache Software License
Requires-Python: >=3.8
License-File: LICENSE
Requires-Dist: click
Requires-Dist: ticktick-py
Requires-Dist: sqlite-utils
Requires-Dist: python-dotenv
Provides-Extra: test
Requires-Dist: pytest ; extra == 'test'
Requires-Dist: ruff ; extra == 'test'
